django_simple_api_proxy/__init__.py
django_simple_api_proxy/admin.py
django_simple_api_proxy/apps.py
django_simple_api_proxy/models.py
django_simple_api_proxy/tests.py
django_simple_api_proxy/urls.py
django_simple_api_proxy/views.py
django_simple_api_proxy/migrations/__init__.py
django_simple_api_proxy-1.0.2.dist-info/LICENSE
django_simple_api_proxy-1.0.2.dist-info/METADATA
django_simple_api_proxy-1.0.2.dist-info/WHEEL
django_simple_api_proxy-1.0.2.dist-info/top_level.txt
django_simple_api_proxy-1.0.2.dist-info/RECORD
