Metadata-Version: 2.1
Name: django-simple-api-proxy
Version: 1.0.2
Summary: Easy to proxy any APIs you want.
Home-page: https://github.com/natlee/Django-Simple-API-Proxy
Author: Nat Lee
Author-email: natlee.work@gmail.com
Project-URL: Documentation, https://github.com/natlee/Django-Simple-API-Proxy
Project-URL: Bug Reports, https://github.com/natlee/Django-Simple-API-Proxy/issues
Project-URL: Source Code, https://github.com/natlee/Django-Simple-API-Proxy
Keywords: django,api,proxy,proxy pass
Classifier: Development Status :: 5 - Production/Stable
Classifier: Intended Audience :: Developers
Classifier: Topic :: Software Development :: Build Tools
Classifier: Programming Language :: Python :: 3
Classifier: Programming Language :: Python :: 3.8
Classifier: Programming Language :: Python :: 3.9
Classifier: Programming Language :: Python :: 3 :: Only
Classifier: License :: OSI Approved :: MIT License
Classifier: Operating System :: OS Independent
Requires-Python: >=3.8
License-File: LICENSE
Requires-Dist: django (>=4.0.0)
Requires-Dist: requests
Requires-Dist: loguru
Requires-Dist: djangorestframework
Provides-Extra: dev
Requires-Dist: check-manifest ; extra == 'dev'
